logkit/__init__.py
logkit/log.py
logkit/logger.py
logkit/pulse.py
logkit/socket_logger.py
logkit/utils/__init__.py
logkit/utils/pather.py
logkit/utils/truncate.py
logkit-0.4.3.dist-info/METADATA
logkit-0.4.3.dist-info/WHEEL
logkit-0.4.3.dist-info/top_level.txt
logkit-0.4.3.dist-info/RECORD
