Metadata-Version: 2.1
Name: logkit
Version: 0.4.3
Summary: Basic logging wrapper for Python.
Home-page: https://github.com/krinj/logkit
Author: Jakrin Juangbhanich
Author-email: juangbhanich.k@gmail.com
License: UNKNOWN
Platform: UNKNOWN
Classifier: Programming Language :: Python :: 3.6
Requires-Dist: python-dotenv
